{"cameraMode":{"drawMode":0,"name":"Shaded","section":"Shading Mode"},"sceneLighting":true,"audioPlay":false,"sceneViewState":{"m_AlwaysRefresh":false,"showFog":true,"showSkybox":true,"showFlares":true,"showImageEffects":true,"showParticleSystems":true,"showVisualEffectGraphs":true,"m_FxEnabled":true},"in2DMode":false,"pivot":{"x":0.0,"y":2.0999999046325685,"z":0.21200037002563477},"rotation":{"x":-0.09520789235830307,"y":-0.8998693227767944,"z":0.34644126892089846,"w":-0.2473072111606598},"size":12.075055122375489,"orthographic":false}