<Properties StartupConfiguration="{A79F4D05-8018-189D-1E2B-66AE9AB7AA56}|">
  <MonoDevelop.Ide.Workbench ActiveDocument="Assets/03.Scripts/PlayerPunchController.cs">
    <Files>
      <File FileName="Assets/03.Scripts/PlayerPunchController.cs" Line="14" Column="38" />
      <File FileName="Assets/07_InputActions/PlayerInputActions.cs" />
    </Files>
  </MonoDevelop.Ide.Workbench>
  <MonoDevelop.Ide.DebuggingService.PinnedWatches />
  <MonoDevelop.Ide.Workspace ActiveConfiguration="Debug" />
  <MonoDevelop.Ide.ItemProperties.Assembly-CSharp PreferredExecutionTarget="c812022e-318f-4a7c-b781-df552c0f8be2" />
  <MonoDevelop.Ide.DebuggingService.Breakpoints>
    <BreakpointStore />
  </MonoDevelop.Ide.DebuggingService.Breakpoints>
  <MultiItemStartupConfigurations />
</Properties>